with_contextvars.py
with_contextvars-0.1.2.dist-info/LICENSE
with_contextvars-0.1.2.dist-info/METADATA
with_contextvars-0.1.2.dist-info/WHEEL
with_contextvars-0.1.2.dist-info/RECORD
