Metadata-Version: 2.1
Name: with-contextvars
Version: 0.1.2
Summary: Context manager for setting contextvars variables
Home-page: https://github.com/bob1de/python-with-contextvars
License: MIT
Author: Robert Schindler
Author-email: dev@bob1.de
Requires-Python: >=3.7,<4.0
Classifier: License :: OSI Approved :: MIT License
Classifier: Programming Language :: Python :: 3
Classifier: Programming Language :: Python :: 3.7
Classifier: Programming Language :: Python :: 3.8
Classifier: Programming Language :: Python :: 3.9
Classifier: Programming Language :: Python :: 3.10
Classifier: Programming Language :: Python :: 3.11
Classifier: Programming Language :: Python :: 3.12
